galahad/__init__.py
galahad/authentication.py
galahad/dataset.py
galahad/display.py
galahad/history.py
galahad/sessions.py
galahad/tool.py
galahad/utils.py
galaxy_galahad-24.8.data/data/share/jupyter/nbtools/galahad.json
galaxy_galahad-24.8.dist-info/LICENSE.txt
galaxy_galahad-24.8.dist-info/METADATA
galaxy_galahad-24.8.dist-info/WHEEL
galaxy_galahad-24.8.dist-info/top_level.txt
galaxy_galahad-24.8.dist-info/RECORD
