Metadata-Version: 2.1
Name: galaxy-galahad
Version: 24.8
Summary: Connect to the Galaxy platform within Jupyter notebooks
Home-page: https://github.com/g2nb/galahad
Download-URL: https://github.com/g2nb/galahad/archive/24.08.tar.gz
Author: Thorin Tabor
Author-email: tmtabor@cloud.ucsd.edu
License: BSD
Keywords: galaxy,genomics,bioinformatics,ipython,jupyter
Classifier: Development Status :: 5 - Production/Stable
Classifier: Intended Audience :: Science/Research
Classifier: Intended Audience :: Developers
Classifier: Topic :: Scientific/Engineering :: Bio-Informatics
Classifier: License :: OSI Approved :: BSD License
Classifier: Programming Language :: Python :: 3.9
Classifier: Programming Language :: Python :: 3.10
Classifier: Programming Language :: Python :: 3.11
Classifier: Framework :: Jupyter
License-File: LICENSE.txt
Requires-Dist: bioblend
Requires-Dist: nbtools (>=23.4)
Requires-Dist: jupyterlab (<4,>=3.6)
Requires-Dist: ipywidgets (>=8.0.0)
Requires-Dist: pandas
